tuition_calc/__init__.py
tuition_calc/school.py
tution_calc-0.0.2.dist-info/LICENSE
tution_calc-0.0.2.dist-info/METADATA
tution_calc-0.0.2.dist-info/WHEEL
tution_calc-0.0.2.dist-info/top_level.txt
tution_calc-0.0.2.dist-info/RECORD
