Metadata-Version: 2.1
Name: tution-calc
Version: 0.0.2
Summary: Basic tution rate calculator
Author: Avais Akhtar
Author-email: avais.akhtar@mirada-medical.com
License: UNKNOWN
Platform: UNKNOWN
Classifier: Programming Language :: Python :: 3
Classifier: License :: OSI Approved :: MIT License
Classifier: Operating System :: OS Independent
Requires-Python: >=3.7
License-File: LICENSE
